conlang_gpt/__init__.py
conlang_gpt/__main__.py
conlang_gpt/cli.py
conlang_gpt/command/__init__.py
conlang_gpt/command/create.py
conlang_gpt/command/improve.py
conlang_gpt/command/modify.py
conlang_gpt/command/translate.py
conlang_gpt/embeddings.py
conlang_gpt/language.py
conlang_gpt/openai.py
conlang_gpt-0.4.0.dist-info/LICENSE
conlang_gpt-0.4.0.dist-info/METADATA
conlang_gpt-0.4.0.dist-info/WHEEL
conlang_gpt-0.4.0.dist-info/entry_points.txt
conlang_gpt-0.4.0.dist-info/RECORD
