Metadata-Version: 2.1
Name: conlang-gpt
Version: 0.4.0
Summary: ChatGPT language generator and translator
Home-page: https://github.com/clabe45/conlang-gpt
License: MIT
Keywords: conlang,chatgpt,gpt 4,openai
Author: Caleb Sacks
Author-email: 16855387+clabe45@users.noreply.github.com
Requires-Python: >=3.9,<4.0
Classifier: License :: OSI Approved :: MIT License
Classifier: Programming Language :: Python :: 3
Classifier: Programming Language :: Python :: 3.9
Classifier: Programming Language :: Python :: 3.10
Classifier: Programming Language :: Python :: 3.11
Requires-Dist: click (>=8.1.3,<9.0.0)
Requires-Dist: langchain (>=0.0.314,<0.0.315)
Requires-Dist: openai[embeddings] (>=0.27.8,<0.28.0)
Requires-Dist: python-dotenv (>=1.0.0,<2.0.0)
Requires-Dist: sentence-transformers (>=2.2.2,<3.0.0)
